sqlpyhelper/__init__.py
sqlpyhelper/db_helper.py
sqlpyhelper-0.1.3.dist-info/licenses/LICENSE
sqlpyhelper-0.1.3.dist-info/METADATA
sqlpyhelper-0.1.3.dist-info/WHEEL
sqlpyhelper-0.1.3.dist-info/top_level.txt
sqlpyhelper-0.1.3.dist-info/RECORD
