Metadata-Version: 2.4
Name: SQLPyHelper
Version: 0.1.3
Summary: A simple SQL database helper package for Python.
Author: Adebayo Olaonipekun
Author-email: pekunmi@live.com
Classifier: Programming Language :: Python :: 3
Classifier: Development Status :: 5 - Production/Stable
Classifier: Intended Audience :: Developers
Classifier: Topic :: Database :: Database Engines/Servers
Classifier: Operating System :: OS Independent
Classifier: License :: OSI Approved :: MIT License
Requires-Python: >=3.8
License-File: LICENSE
Requires-Dist: psycopg2
Requires-Dist: mysql-connector-python
Requires-Dist: pyodbc
Requires-Dist: cx_Oracle
Requires-Dist: python-dotenv
Provides-Extra: mysql
Requires-Dist: mysql-connector-python; extra == "mysql"
Provides-Extra: postgres
Requires-Dist: psycopg2; extra == "postgres"
Provides-Extra: oracle
Requires-Dist: cx_Oracle; extra == "oracle"
Provides-Extra: sqlserver
Requires-Dist: pyodbc; extra == "sqlserver"
Provides-Extra: sqlite
Dynamic: author
Dynamic: author-email
Dynamic: classifier
Dynamic: description
Dynamic: description-content-type
Dynamic: license-file
Dynamic: provides-extra
Dynamic: requires-dist
Dynamic: requires-python
Dynamic: summary
